amoeba/__init__.py
amoeba/build_ext_option.py
amoeba/build_extension.py
amoeba/commands.py
amoeba/extension.py
amoeba/sdist_command.py
amoeba_build-0.0.12.dist-info/LICENSE
amoeba_build-0.0.12.dist-info/METADATA
amoeba_build-0.0.12.dist-info/WHEEL
amoeba_build-0.0.12.dist-info/top_level.txt
amoeba_build-0.0.12.dist-info/RECORD
