Metadata-Version: 2.1
Name: amoeba-build
Version: 0.0.12
Summary: Setuptools extension to build and package CMake projects.
Home-page: https://github.com/claudioperez/amoeba-build
Author: Diego Ferigo
Author-email: dgferigo@gmail.com
License: MIT
Project-URL: Changelog, https://github.com/claudioperez/amoeba-build/releases
Project-URL: Source, https://github.com/claudioperez/amoeba-build
Project-URL: Tracker, https://github.com/claudioperez/amoeba-build/issues
Keywords: setuptools,extension,cmake,build,package,pypi
Platform: any
Classifier: Development Status :: 4 - Beta
Classifier: Intended Audience :: Developers
Classifier: License :: OSI Approved :: MIT License
Classifier: Operating System :: OS Independent
Classifier: Programming Language :: Python :: 3 :: Only
Classifier: Programming Language :: Python :: 3
Classifier: Programming Language :: Python :: 3.6
Classifier: Programming Language :: Python :: 3.7
Classifier: Programming Language :: Python :: 3.8
Classifier: Programming Language :: Python :: 3.9
Classifier: Programming Language :: Python :: 3.10
Classifier: Programming Language :: Python :: Implementation :: CPython
Classifier: Topic :: Software Development :: Build Tools
Classifier: Topic :: Software Development :: Libraries :: Python Modules
Classifier: Topic :: System :: Archiving :: Packaging
Requires-Python: >=3.6
License-File: LICENSE
Requires-Dist: GitPython
Requires-Dist: setuptools-scm
